README.rst
setup.py
gcmstools/__init__.py
gcmstools/calibration.py
gcmstools/datastore.py
gcmstools/filetypes.py
gcmstools/fitting.py
gcmstools/general.py
gcmstools/isotope.py
gcmstools/reference.py
gcmstools.egg-info/PKG-INFO
gcmstools.egg-info/SOURCES.txt
gcmstools.egg-info/dependency_links.txt
gcmstools.egg-info/requires.txt
gcmstools.egg-info/top_level.txt