Metadata-Version: 1.1
Name: gcmstools
Version: 0.2.0
Summary: Tools for working with GCMS files.
Home-page: https://github.com/rnelsonchem/gcmstools
Author: Ryan Nelson
Author-email: rnelsonchem@gmail.com
License: BSD
Keywords: gcms aia nnls
Platform: UNKNOWN
Classifier: Development Status :: 4 - Beta
Classifier: Intended Audience :: Science/Research
Classifier: License :: OSI Approved :: BSD License
Classifier: Programming Language :: Python :: 2
Classifier: Programming Language :: Python :: 2.7
Classifier: Programming Language :: Python :: 3
Classifier: Programming Language :: Python :: 3.4
